tests/__init__.py
ziim/__init__.py
ziim/__main__.py
ziim/example.py
ziim/module.py
ziim-0.0.9.2.data/scripts/ziim
ziim-0.0.9.2.dist-info/LICENSE.txt
ziim-0.0.9.2.dist-info/METADATA
ziim-0.0.9.2.dist-info/WHEEL
ziim-0.0.9.2.dist-info/top_level.txt
ziim-0.0.9.2.dist-info/RECORD
