Metadata-Version: 2.1
Name: ziim
Version: 0.0.9.2
Summary: Let your CLI find available solutions for errors/exceptions in your code for you, no need open a Browser. and do something yourself, you just have to select the forum
Home-page: https://github.com/sanix-darker/ziim
Author: Sanix-darker
Author-email: s4nixd@gmail.com
License: UNKNOWN
Platform: UNKNOWN
Classifier: Programming Language :: Python :: 3
Classifier: License :: OSI Approved :: MIT License
Classifier: Operating System :: OS Independent
Requires-Python: >=3.6
